garpix_faq/CHANGELOG.md
garpix_faq/MANIFEST.in
garpix_faq/README.md
garpix_faq/__init__.py
garpix_faq/admin.py
garpix_faq/apps.py
garpix_faq/models.py
garpix_faq/serializers.py
garpix_faq/setup.py
garpix_faq/tests.py
garpix_faq/urls.py
garpix_faq/views.py
garpix_faq/__pycache__/__init__.cpython-310.pyc
garpix_faq/__pycache__/admin.cpython-310.pyc
garpix_faq/__pycache__/apps.cpython-310.pyc
garpix_faq/__pycache__/models.cpython-310.pyc
garpix_faq/__pycache__/serializers.cpython-310.pyc
garpix_faq/__pycache__/tests.cpython-310.pyc
garpix_faq/__pycache__/urls.cpython-310.pyc
garpix_faq/__pycache__/views.cpython-310.pyc
garpix_faq-1.0.1.dist-info/METADATA
garpix_faq-1.0.1.dist-info/WHEEL
garpix_faq-1.0.1.dist-info/top_level.txt
garpix_faq-1.0.1.dist-info/RECORD
